odoo8_addon_account_fiscal_position_partner_type-8.0.1.0.0.99.dev2-py3.8-nspkg.pth
odoo_addons/account_fiscal_position_partner_type/README.rst
odoo_addons/account_fiscal_position_partner_type/__init__.py
odoo_addons/account_fiscal_position_partner_type/__openerp__.py
odoo_addons/account_fiscal_position_partner_type/i18n/account_fiscal_position_partner_type.pot
odoo_addons/account_fiscal_position_partner_type/models/__init__.py
odoo_addons/account_fiscal_position_partner_type/models/account_fiscal_position.py
odoo_addons/account_fiscal_position_partner_type/models/res_company.py
odoo_addons/account_fiscal_position_partner_type/models/res_partner.py
odoo_addons/account_fiscal_position_partner_type/readme/CONFIGURE.rst
odoo_addons/account_fiscal_position_partner_type/readme/CONTRIBUTORS.rst
odoo_addons/account_fiscal_position_partner_type/readme/DESCRIPTION.rst
odoo_addons/account_fiscal_position_partner_type/readme/USAGE.rst
odoo_addons/account_fiscal_position_partner_type/static/description/icon.png
odoo_addons/account_fiscal_position_partner_type/static/description/index.html
odoo_addons/account_fiscal_position_partner_type/tests/__init__.py
odoo_addons/account_fiscal_position_partner_type/tests/test_account_fiscal_position_partner_type.py
odoo_addons/account_fiscal_position_partner_type/views/account_fiscal_position.xml
odoo_addons/account_fiscal_position_partner_type/views/res_company.xml
odoo_addons/account_fiscal_position_partner_type/views/res_partner.xml
odoo8_addon_account_fiscal_position_partner_type-8.0.1.0.0.99.dev2.dist-info/METADATA
odoo8_addon_account_fiscal_position_partner_type-8.0.1.0.0.99.dev2.dist-info/WHEEL
odoo8_addon_account_fiscal_position_partner_type-8.0.1.0.0.99.dev2.dist-info/namespace_packages.txt
odoo8_addon_account_fiscal_position_partner_type-8.0.1.0.0.99.dev2.dist-info/top_level.txt
odoo8_addon_account_fiscal_position_partner_type-8.0.1.0.0.99.dev2.dist-info/RECORD
