Metadata-Version: 2.1
Name: odoo8-addon-account-fiscal-position-partner-type
Version: 8.0.1.0.0.99.dev2
Summary: Account Fiscal Position Partner Type
Home-page: https://github.com/OCA/account-fiscal-rule
Author: Sygel Technology,Odoo Community Association (OCA)
Author-email: support@odoo-community.org
License: AGPL-3
Platform: UNKNOWN
Classifier: Programming Language :: Python
Classifier: Framework :: Odoo
Classifier: License :: OSI Approved :: GNU Affero General Public License v3
Classifier: Development Status :: 5 - Production/Stable
Requires-Python: ~=2.7
Requires-Dist: odoo (<9.0a,>=8.0a)
